Metadata-Version: 1.0
Name: fawentus-generate-latex
Version: 0.0
Summary: Generate latex code
Home-page: UNKNOWN
Author: UNKNOWN
Author-email: fawentus@gmail.com
License: UNKNOWN
Platform: UNKNOWN
